setup.py
bt_tools/__init__.py
bt_tools/hub.py
bt_tools.egg-info/PKG-INFO
bt_tools.egg-info/SOURCES.txt
bt_tools.egg-info/dependency_links.txt
bt_tools.egg-info/top_level.txt