Metadata-Version: 1.0
Name: bt-tools
Version: 0.0.0
Summary: APIs for getting data from a BT Smart Hub
Home-page: https://github.com/wllkle/bt_tools
Author: Rob Wilkie
Author-email: hello@wilkie.io
License: MIT
Platform: UNKNOWN
